MachineHelper/ClassifierModel.py
MachineHelper/DataProcessing.py
MachineHelper/__init__.py
MachineHelper-0.0.3.dist-info/LICENSE.txt
MachineHelper-0.0.3.dist-info/METADATA
MachineHelper-0.0.3.dist-info/WHEEL
MachineHelper-0.0.3.dist-info/top_level.txt
MachineHelper-0.0.3.dist-info/RECORD
