Metadata-Version: 2.1
Name: MachineHelper
Version: 0.0.3
Summary: Useful tools to work with Machine Learning in python
Home-page: https://github.com/vSasakiv/MachineHelper
Author: Vitor Sasaki Venzel
Author-email: vitorsakivenzelv@gmail.com
License: MIT
Download-URL: https://pypi.org/project/MachineHelper2/
Keywords: Sklearn,Machine Learning,Pandas
Platform: UNKNOWN
Requires-Dist: sklearn
Requires-Dist: numpy
Requires-Dist: pandas
